setup.py
iscconf/__init__.py
iscconf/parser.py
iscconf.egg-info/PKG-INFO
iscconf.egg-info/SOURCES.txt
iscconf.egg-info/dependency_links.txt
iscconf.egg-info/requires.txt
iscconf.egg-info/top_level.txt