Metadata-Version: 1.0
Name: iscconf
Version: 1.0.0dev6
Summary: Parser for ISC configuration files.
Home-page: https://bitbucket.org/thesheep/iscconf/
Author: Radomir Dopieralski
Author-email: devel@sheep.art.pl
License: BSD
Keywords: isc parser config configuration
Platform: any
